{
    "DataList": {
        "[NX] Centreon Nutanix SNMP Threshold Units List": {
            "entries": [
                {
                    "entry_name": "%",
                    "entry_value": "Percentage",
                    "format": "string",
                    "allowed_roles": null
                },
                {
                    "entry_name": "B",
                    "entry_value": "Bytes",
                    "format": "string",
                    "allowed_roles": null
                }
            ],
            "list_name": "[NX] Centreon Nutanix SNMP Threshold Units List",
            "owner": "pb00269",
            "uuid": "8d7d218b-ff3e-4979-b12a-7462000000dc"
        }
    }
}